Workbook

Sheet ⚙ Rates & Assumptions
A1: BC Web Creator — Cost & Pricing Assumptions
A2: Blue cells = inputs you can change | All prices in CAD
A4: ⏱ YOUR LABOUR & TIME RATES
A5: Your hourly rate (target) | B5: 25 | C5: What you want to earn per hour
A6: Design/prep time — simple logo (min) | B6: 20 | C6: Minutes to prep a clean vector file
A7: Design/prep time — complex logo (min) | B7: 45 | C7: Minutes for intricate designs or conversions
A8: Cricut cut time per decal (min) | B8: 3 | C8: Average cut time for a 4" decal
A9: Weeding time — simple decal (min) | B9: 5 | C9: Time to weed clean designs
A10: Weeding time — complex decal (min) | B10: 18 | C10: Intricate designs, lace borders, fine detail
A11: Press time per shirt (min) | B11: 8 | C11: Including HTV placement and pressing
A12: Packing & transfer tape per decal (min) | B12: 3 | C12: Applying transfer tape, trimming, packaging
A13: Order admin time (min) | B13: 10 | C13: Messaging client, invoicing, file review
A15: 🎨 VINYL & MATERIALS COSTS
A16: Permanent vinyl cost per sq ft (Oracal 651) | B16: 0.8 | C16: Standard permanent vinyl — great for decals
A17: HTV vinyl cost per sq ft (heat transfer) | B17: 1.2 | C17: Iron-on / heat transfer vinyl for shirts
A18: Specialty vinyl premium (reflective/holographic) | B18: 2.5 | C18: Extra cost per sq ft over standard
A19: Transfer tape cost per sq ft | B19: 0.15 | C19: Needed for applying decals
A20: Average vinyl used — small decal (sq ft) | B20: 0.1 | C20: Up to 3" × 3"
A21: Average vinyl used — medium decal (sq ft) | B21: 0.25 | C21: 3" – 6"
A22: Average vinyl used — large decal (sq ft) | B22: 0.7 | C22: 6" – 12"
A23: Average HTV used — shirt front only (sq ft) | B23: 0.55 | C23: Standard chest logo
A24: Average HTV used — front + back (sq ft) | B24: 1.1 | C24: Double-sided print
A26: 👕 BLANK GARMENT WHOLESALE COSTS (You Supply)
A27: Budget cotton blank (Gildan 5000) | B27: 4.5 | C27: Wholesale per shirt — order to fulfil each job
A28: Mid-range blank (Bella+Canvas 3001) | B28: 7.5 | C28: Popular fitted unisex — great quality
A29: Premium blank (Next Level 6210) | B29: 10 | C29: Premium ring-spun cotton blend
A30: Hoodie blank (Gildan 18500) | B30: 14 | C30: Wholesale per hoodie
A31: Toque / beanie blank | B31: 6 | C31: Per unit wholesale
A32: Shipping to you (per garment, avg) | B32: 1.25 | C32: Estimated freight cost per piece from wholesaler
A33: Minimum order from wholesaler | B33: 12 | C33: Typical minimum — order per job, not in advance
A35: 📦 MAKE-TO-ORDER POLICY NOTES
A36: ✅ Orders are made-to-order only — no inventory kept on hand
A37: ✅ Customer must confirm size, colour, and quantity BEFORE you place blank order
A38: ✅ Require 50% deposit upfront to cover blank and material costs
A39: ✅ Turnaround: 5–10 business days from deposit received (allows time to order blanks)
A40: ✅ CSG (customer supplies garment): reduces your risk — just charge pressing + design fee
A41: ⚠️ Liability waiver required for CSG — you are not responsible for fabric damage
A42: ⚠️ Polyester, nylon, and athletic-wear fabrics are HIGH RISK — do not press without testing
A43: ⚠️ If customer supplies garments, inspect fabric content before accepting the job

Sheet 🏷 Decal Calculator
A1: BC Web Creator — Vinyl Decal Job Cost Calculator
A2: Enter job details in BLUE cells. Costs calculate automatically.
A4: JOB INPUTS
A5: Decal size | B5: — | E5: Small / Medium / Large — for reference only
A6: Quantity of decals | B6: 10 | E6: Number of decals in this order
A7: Design complexity | B7: 0 | E7: Simple or Complex — affects weeding time
A8: Specialty vinyl? (1=Yes 0=No) | B8: 0 | E8: Reflective, holographic, metallic
A9: New logo? Needs setup? (1=Yes 0=No) | B9: 1 | E9: First time client or non-vector file
A10: Vinyl sq ft per decal | B10: 0.25 | E10: From assumptions sheet — update to match size
A11: COST BREAKDOWN (per decal)
A12: Cost Item | B12: Unit Cost | C12: Per Decal | D12: Job Total | E12: Notes
A13: Vinyl material | B13: ='⚙ Rates & Assumptions'!B19 -> 0.15 | C13: =B13*B10 -> 0.0375 | D13: =C13*B6 -> 0.375 | E13: Permanent vinyl (Oracal 651)
A14: Specialty vinyl upcharge | B14: ='⚙ Rates & Assumptions'!B21 -> 0.25 | C14: =B14*B10*B8 -> 0 | D14: =C14*B6 -> 0 | E14: Only charged if specialty vinyl selected
A15: Transfer tape | B15: ='⚙ Rates & Assumptions'!B22 -> 0.7 | C15: =B15*B10 -> 0.175 | D15: =C15*B6 -> 1.75 | E15: Applied after weeding
A16: Cut time labour | B16: ='⚙ Rates & Assumptions'!B5 -> 25 | C16: ='⚙ Rates & Assumptions'!B8/60*'⚙ Rates & Assumptions'!B5 -> 1.25 | D16: =C16*B6 -> 12.5 | E16: Cricut cut time × hourly rate
A17: Weeding labour | B17: ='⚙ Rates & Assumptions'!B5 -> 25 | C17: =IF(B7=1,'⚙ Rates & Assumptions'!B10,'⚙ Rates & Assumptions'!B9)/60*'⚙ Rates & Assumptions'!B5 -> 2.0833333 | D17: =C17*B6 -> 20.833333 | E17: Simple vs complex weeding time
A18: Packing & transfer apply | B18: ='⚙ Rates & Assumptions'!B5 -> 25 | C18: ='⚙ Rates & Assumptions'!B12/60*'⚙ Rates & Assumptions'!B5 -> 1.25 | D18: =C18*B6 -> 12.5 | E18: Applying transfer tape and packaging
A19: Logo setup / file prep (one-time) | B19: ='⚙ Rates & Assumptions'!B5 -> 25 | C19: =IF(B9=1,'⚙ Rates & Assumptions'!B6/60*'⚙ Rates & Assumptions'!B5,0) -> 8.3333333 | D19: =C19 -> 8.3333333 | E19: One-time charge — not multiplied by quantity
A20: Order admin time | B20: ='⚙ Rates & Assumptions'!B5 -> 25 | C20: ='⚙ Rates & Assumptions'!B13/60*'⚙ Rates & Assumptions'!B5 -> 4.1666667 | D20: =C20 -> 4.1666667 | E20: One-time per order admin charge
A22: JOB SUMMARY
A23: Total job cost (materials + labour) | D23: =SUM(D13:D20) -> 60.458333
A24: Cost per decal | C24: =D23/B6 -> 6.0458333
A25: Suggested sell price per decal (2× markup) | C25: =C24*2 -> 12.091667
A26: Suggested sell price per decal (2.5× markup) | C26: =C24*2.5 -> 15.114583
A27: Suggested job total (2× markup) | D27: =D23*2 -> 120.91667
A28: Profit at 2× markup | D28: =D27-D23 -> 60.458333
A29: Profit margin at 2× markup | D29: =D28/D27 -> 0.5

Sheet 👕 Shirt Calculator
A1: BC Web Creator — T-Shirt Job Cost Calculator
A2: Blue cells = your inputs. Switch between Customer Supplies Garment (CSG) or You Supply modes.
A4: JOB INPUTS
A5: Input | B5: Value | E5: Notes
A6: Quantity of shirts | B6: 10 | E6: Number of shirts in this order
A7: Supply mode (1=You Supply, 0=CSG) | B7: 1 | E7: 1 = BC Web Creator buys blanks. 0 = Customer brings shirts
A8: Garment type (1=Budget 2=Mid 3=Premium) | B8: 1 | E8: 1=Gildan $4.50 2=B+C $7.50 3=Next Level $10
A9: Front + back print? (1=Yes 0=No) | B9: 0 | E9: Doubles HTV and press time
A10: Design complexity (1=Complex 0=Simple) | B10: 0 | E10: Affects design prep time
A11: New logo / needs setup? (1=Yes 0=No) | B11: 1 | E11: One-time file prep charge
A13: COST BREAKDOWN
A14: Cost Item | B14: Unit Cost | C14: Per Shirt | D14: Job Total | E14: Notes
A15: Blank garment cost | B15: =IF(B8=1,'⚙ Rates & Assumptions'!B32,IF(B8=2,'⚙ Rates & Assumptions'!B33,'⚙ Rates & Assumptions'!B34)) -> 1.25 | C15: =IF(B7=1,B15+'⚙ Rates & Assumptions'!B37,0) -> 1.25 | D15: =C15*B6 -> 12.5 | E15: Zero if customer supplies garment (CSG)
A16: HTV vinyl material | B16: ='⚙ Rates & Assumptions'!B20 -> 0.1 | C16: =IF(B9=1,'⚙ Rates & Assumptions'!B29,'⚙ Rates & Assumptions'!B28)*B16 -> 0.75 | D16: =C16*B6 -> 7.5 | E16: Front only vs front+back HTV usage
A17: Design / file prep (one-time) | B17: ='⚙ Rates & Assumptions'!B5 -> 25 | C17: =IF(B11=1,IF(B10=1,'⚙ Rates & Assumptions'!B7,'⚙ Rates & Assumptions'!B6)/60*'⚙ Rates & Assumptions'!B5,0) -> 8.3333333 | D17: =C17 -> 8.3333333 | E17: One-time per job, not per shirt
A18: Heat press labour | B18: ='⚙ Rates & Assumptions'!B5 -> 25 | C18: ='⚙ Rates & Assumptions'!B11/60*'⚙ Rates & Assumptions'!B5*IF(B9=1,1.5,1) -> 3.3333333 | D18: =C18*B6 -> 33.333333 | E18: ×1.5 for front+back orders
A19: HTV weeding labour | B19: ='⚙ Rates & Assumptions'!B5 -> 25 | C19: =IF(B10=1,'⚙ Rates & Assumptions'!B10,'⚙ Rates & Assumptions'!B9)/60*'⚙ Rates & Assumptions'!B5 -> 2.0833333 | D19: =C19*B6 -> 20.833333 | E19: Simple vs complex design weeding
A20: Order admin time (one-time) | B20: ='⚙ Rates & Assumptions'!B5 -> 25 | C20: ='⚙ Rates & Assumptions'!B13/60*'⚙ Rates & Assumptions'!B5 -> 4.1666667 | D20: =C20 -> 4.1666667 | E20: One-time per order
A21: ⚠️ CSG Mode: Customer supplies garments — always get signed liability waiver. Not responsible for fabric damage.
A23: JOB SUMMARY
A24: Total job cost (all in) | D24: =SUM(D15:D20) -> 86.666667
A25: Cost per shirt | C25: =D24/B6 -> 8.6666667
A26: Mode | B26: =IF(B7=1,"You Supply Garments","Customer Supplies Garment (CSG)") -> You Supply Garments
A27: Suggested sell price per shirt (2× markup) | C27: =C25*2 -> 17.333333
A28: Suggested sell price per shirt (2.5× markup) | C28: =C25*2.5 -> 21.666667
A29: Suggested job total (2× markup) | D29: =D24*2 -> 173.33333
A30: Profit at 2× markup | D30: =D29-D24 -> 86.666667
A31: Profit margin at 2× markup | D31: =D30/D29 -> 0.5

Sheet 💰 Quick Price Reference
A1: BC Web Creator — Quick Pricing Reference (CAD)
A2: For internal use and client quotes. All prices make-to-order.
A4: VINYL DECALS
A5: Size | B5: Small Batch (10–49) | C5: Bulk (50+) | D5: Notes
A6: Small (up to 3") | B6: $3.50 – $5.00 ea. | C6: $1.50 – $2.50 ea. | D6: Standard permanent vinyl
A7: Medium (3" – 6") | B7: $7.00 – $10.00 ea. | C7: $4.00 – $6.00 ea.
A8: Large (6" – 12") | B8: $20.00 – $28.00 ea. | C8: $12.00 – $16.00 ea.
A9: Specialty vinyl | B9: +$2.00–$5.00 ea. | C9: +$2.00–$5.00 ea. | D9: Reflective / holographic / metallic
A10: Complex design fee | B10: +15%–25% | C10: +15%–25% | D10: Intricate weeding required
A11: Logo setup fee | B11: $15.00–$30.00 | C11: $15.00–$30.00 | D11: One-time, non-vector files only
A14: CUSTOM T-SHIRTS — YOU SUPPLY GARMENT
A15: Quantity | B15: Budget Cotton | C15: Premium Blend | D15: Notes
A16: Individual (1–9) | B16: $25 – $35 | C16: $35 – $50 | D16: Includes HTV, pressing, weeding
A17: Team / Small Biz (10–49) | B17: $18 – $22 ea. | C17: $25 – $32 ea. | D17: Bulk rate applied
A18: Bulk (50+) | B18: $14 – $16 ea. | C18: $18 – $24 ea. | D18: Best per-unit rate
A19: Front + Back add-on | B19: +$5–$10/garment | C19: +$5–$10/garment | D19: Double press and HTV
A20: Oversized (>12"×12") | B20: +$2–$5/shirt | C20: +$2–$5/shirt | D20: Extra material and time
A21: Logo setup fee | B21: $15–$30 (once) | C21: $15–$30 (once) | D21: First time / non-vector file
A24: CUSTOM T-SHIRTS — CUSTOMER SUPPLIES GARMENT (CSG)
A25: Service | B25: Price per Shirt | D25: Notes
A26: Press only (your HTV design pre-made) | B26: $10 – $15 | D26: Customer brings shirt, you press
A27: Design + press (simple 1-colour) | B27: $15 – $20 | D27: Includes HTV cutting and weeding
A28: Design + press (complex / multi-layer) | B28: $20 – $30 | D28: Detailed designs, layered vinyl
A29: WAIVER REQUIRED | B29: Must sign before work begins | D29: ⚠️ Not liable for garment damage
A30: Accepted fabrics | B30: 100% cotton, 50/50 blends only | D30: ⚠️ No polyester, nylon, athletic wear
A33: MAKE-TO-ORDER POLICY
A34: Deposit required | B34: 50% upfront | C34: Covers blanks + materials before order placed
A35: Turnaround time | B35: 5–10 business days | C35: From deposit received — allows time to source blanks
A36: Blank sourcing | B36: Ordered per job — no inventory | C36: S&S Activewear, Alphabroder, or Gildan direct
A37: Size confirmation | B37: Required before order placed | C37: Customer confirms all sizes in writing
A38: Cancellation policy | B38: Deposit non-refundable | C38: Once blanks ordered, job is committed
A39: Revision policy | B39: 1 free revision on designs | C39: Additional revisions at $25/hr
